LFSR_.v
module lfsr #(
    parameter WIDTH = 32,
    parameter TAPS  = 32'h80200003  // Example for 32-bit LFSR
) (
    input         clk,
    input         rst,
    output [WIDTH-1:0] lfsr_out
);

reg [WIDTH-1:0] lfsr_reg;

always @(posedge clk or posedge rst) begin
    if (rst)
        lfsr_reg <= 32'h1;  // Seed
    else
        lfsr_reg <= {lfsr_reg[WIDTH-2:0], ^(lfsr_reg & TAPS)};
end

assign lfsr_out = lfsr_reg;

endmodule
`timescale 1ns/1ps

`timescale 1ns/1ps

module lfsr_tb;
    // Parameter declaration
    parameter WIDTH = 32;

    // Signal declarations
    reg clk;
    reg rst;
    wire [WIDTH-1:0] lfsr_out;

    // Instantiate the LFSR module
    lfsr #(
        .WIDTH(WIDTH),
        .TAPS(32'h80200003)
    ) uut (
        .clk(clk),
        .rst(rst),
        .lfsr_out(lfsr_out)
    );

    // Clock generation: 10 ns period
    initial begin
        clk = 0;
        forever #5 clk = ~clk;
    end

    // Dump waveforms and monitor signals
    initial begin
        $dumpfile("lfsr_tb.vcd");
        $dumpvars(0, lfsr_tb);
        $monitor("Time: %0t | rst: %b | lfsr_out: %h", $time, rst, lfsr_out);
    end

    // Test sequence
    initial begin
        rst = 1;         // Assert reset
        #10;
        rst = 0;         // De-assert reset

        // Run simulation for enough time to observe behavior
        #500;
        $display("Simulation complete at time %0t", $time);
        $finish;
    end
endmodule

lfsr_tb.vcd
$date
	Mon Mar 31 06:42:46 2025
$end
$version
	Icarus Verilog
$end
$timescale
	1ps
$end
$scope module lfsr_tb $end
$var wire 32 ! lfsr_out [31:0] $end
$var parameter 32 " WIDTH $end
$var reg 1 # clk $end
$var reg 1 $ rst $end
$scope module uut $end
$var wire 1 # clk $end
$var wire 32 % lfsr_out [31:0] $end
$var wire 1 $ rst $end
$var parameter 32 & TAPS $end
$var parameter 32 ' WIDTH $end
$var reg 32 ( lfsr_reg [31:0] $end
$upscope $end
$upscope $end
$enddefinitions $end
$comment Show the parameter values. $end
$dumpall
b100000 '
b10000000001000000000000000000011 &
b100000 "
$end
#0
$dumpvars
b1 (
b1 %
1$
0#
b1 !
$end
#5000
1#
#10000
0#
0$
#15000
b11 !
b11 %
b11 (
1#
#20000
0#
#25000
b110 !
b110 %
b110 (
1#
#30000
0#
#35000
b1101 !
b1101 %
b1101 (
1#
#40000
0#
#45000
b11011 !
b11011 %
b11011 (
1#
#50000
0#
#55000
b110110 !
b110110 %
b110110 (
1#
#60000
0#
#65000
b1101101 !
b1101101 %
b1101101 (
1#
#70000
0#
#75000
b11011011 !
b11011011 %
b11011011 (
1#
#80000
0#
#85000
b110110110 !
b110110110 %
b110110110 (
1#
#90000
0#
#95000
b1101101101 !
b1101101101 %
b1101101101 (
1#
#100000
0#
#105000
b11011011011 !
b11011011011 %
b11011011011 (
1#
#110000
0#
#115000
b110110110110 !
b110110110110 %
b110110110110 (
1#
#120000
0#
#125000
b1101101101101 !
b1101101101101 %
b1101101101101 (
1#
#130000
0#
#135000
b11011011011011 !
b11011011011011 %
b11011011011011 (
1#
#140000
0#
#145000
b110110110110110 !
b110110110110110 %
b110110110110110 (
1#
#150000
0#
#155000
b1101101101101101 !
b1101101101101101 %
b1101101101101101 (
1#
#160000
0#
#165000
b11011011011011011 !
b11011011011011011 %
b11011011011011011 (
1#
#170000
0#
#175000
b110110110110110110 !
b110110110110110110 %
b110110110110110110 (
1#
#180000
0#
#185000
b1101101101101101101 !
b1101101101101101101 %
b1101101101101101101 (
1#
#190000
0#
#195000
b11011011011011011011 !
b11011011011011011011 %
b11011011011011011011 (
1#
#200000
0#
#205000
b110110110110110110110 !
b110110110110110110110 %
b110110110110110110110 (
1#
#210000
0#
#215000
b1101101101101101101101 !
b1101101101101101101101 %
b1101101101101101101101 (
1#
#220000
0#
#225000
b11011011011011011011010 !
b11011011011011011011010 %
b11011011011011011011010 (
1#
#230000
0#
#235000
b110110110110110110110100 !
b110110110110110110110100 %
b110110110110110110110100 (
1#
#240000
0#
#245000
b1101101101101101101101000 !
b1101101101101101101101000 %
b1101101101101101101101000 (
1#
#250000
0#
#255000
b11011011011011011011010001 !
b11011011011011011011010001 %
b11011011011011011011010001 (
1#
#260000
0#
#265000
b110110110110110110110100010 !
b110110110110110110110100010 %
b110110110110110110110100010 (
1#
#270000
0#
#275000
b1101101101101101101101000101 !
b1101101101101101101101000101 %
b1101101101101101101101000101 (
1#
#280000
0#
#285000
b11011011011011011011010001010 !
b11011011011011011011010001010 %
b11011011011011011011010001010 (
1#
#290000
0#
#295000
b110110110110110110110100010100 !
b110110110110110110110100010100 %
b110110110110110110110100010100 (
1#
#300000
0#
#305000
b1101101101101101101101000101000 !
b1101101101101101101101000101000 %
b1101101101101101101101000101000 (
1#
#310000
0#
#315000
b11011011011011011011010001010001 !
b11011011011011011011010001010001 %
b11011011011011011011010001010001 (
1#
#320000
0#
#325000
b10110110110110110110100010100011 !
b10110110110110110110100010100011 %
b10110110110110110110100010100011 (
1#
#330000
0#
#335000
b1101101101101101101000101000111 !
b1101101101101101101000101000111 %
b1101101101101101101000101000111 (
1#
#340000
0#
#345000
b11011011011011011010001010001111 !
b11011011011011011010001010001111 %
b11011011011011011010001010001111 (
1#
#350000
0#
#355000
b10110110110110110100010100011110 !
b10110110110110110100010100011110 %
b10110110110110110100010100011110 (
1#
#360000
0#
#365000
b1101101101101101000101000111100 !
b1101101101101101000101000111100 %
b1101101101101101000101000111100 (
1#
#370000
0#
#375000
b11011011011011010001010001111001 !
b11011011011011010001010001111001 %
b11011011011011010001010001111001 (
1#
#380000
0#
#385000
b10110110110110100010100011110011 !
b10110110110110100010100011110011 %
b10110110110110100010100011110011 (
1#
#390000
0#
#395000
b1101101101101000101000111100111 !
b1101101101101000101000111100111 %
b1101101101101000101000111100111 (
1#
#400000
0#
#405000
b11011011011010001010001111001111 !
b11011011011010001010001111001111 %
b11011011011010001010001111001111 (
1#
#410000
0#
#415000
b10110110110100010100011110011110 !
b10110110110100010100011110011110 %
b10110110110100010100011110011110 (
1#
#420000
0#
#425000
b1101101101000101000111100111100 !
b1101101101000101000111100111100 %
b1101101101000101000111100111100 (
1#
#430000
0#
#435000
b11011011010001010001111001111001 !
b11011011010001010001111001111001 %
b11011011010001010001111001111001 (
1#
#440000
0#
#445000
b10110110100010100011110011110010 !
b10110110100010100011110011110010 %
b10110110100010100011110011110010 (
1#
#450000
0#
#455000
b1101101000101000111100111100100 !
b1101101000101000111100111100100 %
b1101101000101000111100111100100 (
1#
#460000
0#
#465000
b11011010001010001111001111001000 !
b11011010001010001111001111001000 %
b11011010001010001111001111001000 (
1#
#470000
0#
#475000
b10110100010100011110011110010000 !
b10110100010100011110011110010000 %
b10110100010100011110011110010000 (
1#
#480000
0#
#485000
b1101000101000111100111100100001 !
b1101000101000111100111100100001 %
b1101000101000111100111100100001 (
1#
#490000
0#
#495000
b11010001010001111001111001000010 !
b11010001010001111001111001000010 %
b11010001010001111001111001000010 (
1#
#500000
0#
#505000
b10100010100011110011110010000100 !
b10100010100011110011110010000100 %
b10100010100011110011110010000100 (
1#
